<?xml version="1.0" encoding="UTF-8"?>
	<GetHotelsDetailsRS Version="1">
		<Success />
		<Hotels>
			<Hotel POICode="5493630" resultcode="0" message="" >
				<Name><![CDATA[UNIVERS HOTEL]]></Name>
				<Address>
					<Address1><![CDATA[C/ René Baulard,13]]></Address1>
					<Address2><![CDATA[AD200, Encamp, Andorra]]></Address2>
					<PostalCode>AD200</PostalCode>
					<CityCode>59324</CityCode>
					<CityName lang="EN">
						<![CDATA[Encamp]]>
					</CityName>
					<CountryCode>AD</CountryCode>
					<CountryName lang="EN">
						<![CDATA[Andorra]]>
					</CountryName>
				</Address>
				<GeoCode>
					<Latitude>42.540306</Latitude>
					<Longitude>1.583405</Longitude>
				</GeoCode>
				<Rating>
					<Score><![CDATA[3]]></Score>
					<Description><![CDATA[]]></Description>
				</Rating>
				<Descriptions>
					<ShortDescriptions>
						<ShortDescription lang="EN"><![CDATA[The perfect establishment to use during the day to enjoy the fun with nature covered in snow. Of particular note are the panoramic views of the mountain. Its 31rooms have been designed to provide the right environment for a welcome rest. The following services are offered Safe in Reception. Facilities include Heating. ]]></ShortDescription>
					<ShortDescription lang="EN"><![CDATA[The rooms have Telephone, TV, Satellite / Cable TV , Central Heating, Bathtub and Room-Service , and among our services and facilities available we have Lifts, Heating, Billiards and Bar Cafeteria. We also have Multilingual Personnel, Nearby Parking , Ski Room, Use of Plug Adapters, Use of Mobile Chargers, Wi-Fi, Tourist Information and Safe in Reception.  Activities and relax: . Cuisine: International. Pets not allowed. Credit Cards: .  ]]></ShortDescription>
					</ShortDescriptions>
					<LongDescriptions>
						<LongDescription lang="EN"><![CDATA[The perfect establishment to use during the day to enjoy the fun with nature covered in snow. Of particular note are the panoramic views of the mountain. Its 31rooms have been designed to provide the right environment for a welcome rest. The following services are offered Safe in Reception. Facilities include Heating. ]]></LongDescription>
					<LongDescription lang="EN"><![CDATA[The rooms have Telephone, TV, Satellite / Cable TV , Central Heating, Bathtub and Room-Service , and among our services and facilities available we have Lifts, Heating, Billiards and Bar Cafeteria. We also have Multilingual Personnel, Nearby Parking , Ski Room, Use of Plug Adapters, Use of Mobile Chargers, Wi-Fi, Tourist Information and Safe in Reception.  Activities and relax: . Cuisine: International. Pets not allowed. Credit Cards: .  ]]></LongDescription>
					</LongDescriptions>
				</Descriptions>
				<CheckInOut>
					<CheckInTime>1400</CheckInTime>
					<CheckOutTime>1200</CheckOutTime>
				</CheckInOut>
				<Facilities>
					<Facility lang="EN">
						<Name><![CDATA[Tourist Destination]]></Name>
						<Description><![CDATA[Mountain/Snow]]></Description>	
					</Facility>
					<Facility lang="EN">
						<Name><![CDATA[Views]]></Name>
						<Description><![CDATA[Mountain]]></Description>	
					</Facility>
					<Facility lang="EN">
						<Name><![CDATA[Views]]></Name>
						<Description><![CDATA[Interior]]></Description>	
					</Facility>
					<Facility lang="EN">
						<Name><![CDATA[Type of Bed ]]></Name>
						<Description><![CDATA[Couple]]></Description>	
					</Facility>
					<Facility lang="EN">
						<Name><![CDATA[Type of Bed ]]></Name>
						<Description><![CDATA[Twin]]></Description>	
					</Facility>
					<Facility lang="EN">
						<Name><![CDATA[Comforts]]></Name>
						<Description><![CDATA[Central Heating]]></Description>	
					</Facility>
					<Facility lang="EN">
						<Name><![CDATA[Other Services]]></Name>
						<Description><![CDATA[Room-Service]]></Description>	
					</Facility>
					<Facility lang="EN">
						<Name><![CDATA[Comforts]]></Name>
						<Description><![CDATA[Telephone]]></Description>	
					</Facility>
					<Facility lang="EN">
						<Name><![CDATA[Our Bathrooms Include]]></Name>
						<Description><![CDATA[Bathtub]]></Description>	
					</Facility>
					<Facility lang="EN">
						<Name><![CDATA[Comforts]]></Name>
						<Description><![CDATA[Blankets]]></Description>	
					</Facility>
					<Facility lang="EN">
						<Name><![CDATA[Reception]]></Name>
						<Description><![CDATA[No 24/24 Reception]]></Description>	
					</Facility>
					<Facility lang="EN">
						<Name><![CDATA[Reception]]></Name>
						<Description><![CDATA[Multilingual Personnel]]></Description>	
					</Facility>
					<Facility lang="EN">
						<Name><![CDATA[Reception]]></Name>
						<Description><![CDATA[Safe in Reception]]></Description>	
					</Facility>
					<Facility lang="EN">
						<Name><![CDATA[Type of Kitchen]]></Name>
						<Description><![CDATA[International]]></Description>	
					</Facility>
					<Facility lang="EN">
						<Name><![CDATA[Restaurants and Bars]]></Name>
						<Description><![CDATA[Dinner Service]]></Description>	
					</Facility>
					<Facility lang="EN">
						<Name><![CDATA[Credit Cards]]></Name>
						<Description><![CDATA[Accepted]]></Description>	
					</Facility>
					<Facility lang="EN">
						<Name><![CDATA[Adapted for the Disabled]]></Name>
						<Description><![CDATA[Adapted Baths]]></Description>	
					</Facility>
					<Facility lang="EN">
						<Name><![CDATA[Comforts]]></Name>
						<Description><![CDATA[Remote Control]]></Description>	
					</Facility>
					<Facility lang="EN">
						<Name><![CDATA[Type of Latest Renovation]]></Name>
						<Description><![CDATA[Rooms]]></Description>	
					</Facility>
					<Facility lang="EN">
						<Name><![CDATA[Comforts]]></Name>
						<Description><![CDATA[Wake-up Service]]></Description>	
					</Facility>
					<Facility lang="EN">
						<Name><![CDATA[Bathroom Amenities]]></Name>
						<Description><![CDATA[Shampoo]]></Description>	
					</Facility>
					<Facility lang="EN">
						<Name><![CDATA[Bathroom Amenities]]></Name>
						<Description><![CDATA[Bath Gel]]></Description>	
					</Facility>
					<Facility lang="EN">
						<Name><![CDATA[Bathroom Amenities]]></Name>
						<Description><![CDATA[Shower Hat]]></Description>	
					</Facility>
					<Facility lang="EN">
						<Name><![CDATA[Our Bathrooms Include]]></Name>
						<Description><![CDATA[Towels]]></Description>	
					</Facility>
					<Facility lang="EN">
						<Name><![CDATA[Comforts]]></Name>
						<Description><![CDATA[TV]]></Description>	
					</Facility>
					<Facility lang="EN">
						<Name><![CDATA[Comforts]]></Name>
						<Description><![CDATA[Satellite / Cable TV]]></Description>	
					</Facility>
					<Facility lang="EN">
						<Name><![CDATA[Reception]]></Name>
						<Description><![CDATA[Ski Room]]></Description>	
					</Facility>
					<Facility lang="EN">
						<Name><![CDATA[Restaurants and Bars]]></Name>
						<Description><![CDATA[Bar Cafeteria]]></Description>	
					</Facility>
					<Facility lang="EN">
						<Name><![CDATA[Hotel Facilities]]></Name>
						<Description><![CDATA[Lifts]]></Description>	
					</Facility>
					<Facility lang="EN">
						<Name><![CDATA[Leisure]]></Name>
						<Description><![CDATA[Television Room]]></Description>	
					</Facility>
					<Facility lang="EN">
						<Name><![CDATA[Restaurants and Bars]]></Name>
						<Description><![CDATA[Lunch Service]]></Description>	
					</Facility>
					<Facility lang="EN">
						<Name><![CDATA[Pets ]]></Name>
						<Description><![CDATA[Pets not allowed]]></Description>	
					</Facility>
					<Facility lang="EN">
						<Name><![CDATA[Adapted for the Disabled]]></Name>
						<Description><![CDATA[Accesses to the Hotel]]></Description>	
					</Facility>
					<Facility lang="EN">
						<Name><![CDATA[Leisure]]></Name>
						<Description><![CDATA[Lounge]]></Description>	
					</Facility>
					<Facility lang="EN">
						<Name><![CDATA[Leisure]]></Name>
						<Description><![CDATA[Billiards]]></Description>	
					</Facility>
					<Facility lang="EN">
						<Name><![CDATA[Parking, Transfers and Hire Services]]></Name>
						<Description><![CDATA[Nearby Parking]]></Description>	
					</Facility>
					<Facility lang="EN">
						<Name><![CDATA[Hotel Facilities]]></Name>
						<Description><![CDATA[Heating]]></Description>	
					</Facility>
				</Facilities>
				<Images>
					<Image>http://988364489.r.cdn77.net/img/poi/2312/32602312.jpg</Image>
					<Image>http://988364489.r.cdn77.net/img/poi/2313/32602313.jpg</Image>
					<Image>http://988364489.r.cdn77.net/img/poi/2314/32602314.jpg</Image>
					<Image>http://988364489.r.cdn77.net/img/poi/2315/32602315.jpg</Image>
				</Images>
				<EssentialInfo>
					
				</EssentialInfo>
				<ContactInfo>
					<Info>
						<Type>Fax</Type>
						<Content><![CDATA[+376 831970]]></Content>
					</Info>
					<Info>
						<Type>Telephone</Type>
						<Content><![CDATA[+376 731105 ]]></Content>
					</Info>
					
				</ContactInfo>
			</Hotel>
		</Hotels>
	</GetHotelsDetailsRS> 
