<?xml version="1.0" encoding="UTF-8"?>
	<GetHotelsDetailsRS Version="1">
		<Success />
		<Hotels>
			<Hotel POICode="5495206" resultcode="0" message="" >
				<Name><![CDATA[CROWNE PLAZA PELICAN WATERS GOLF RESORT]]></Name>
				<Address>
					<Address1><![CDATA[  38 Mahogany Dr, Pelican Waters Caloundra,]]></Address1>
					<Address2><![CDATA[Caloundra, Australia]]></Address2>
					<PostalCode></PostalCode>
					<CityCode>81797</CityCode>
					<CityName lang="EN">
						<![CDATA[Caloundra]]>
					</CityName>
					<CountryCode>AU</CountryCode>
					<CountryName lang="EN">
						<![CDATA[Australia]]>
					</CountryName>
				</Address>
				<GeoCode>
					<Latitude>-26.837015</Latitude>
					<Longitude>153.0915</Longitude>
				</GeoCode>
				<Rating>
					<Score><![CDATA[4]]></Score>
					<Description><![CDATA[]]></Description>
				</Rating>
				<Descriptions>
					<ShortDescriptions>
						</ShortDescriptions>
					<LongDescriptions>
						</LongDescriptions>
				</Descriptions>
				<CheckInOut>
					<CheckInTime>0</CheckInTime>
					<CheckOutTime>0</CheckOutTime>
				</CheckInOut>
				<Facilities>
				</Facilities>
				<Images>
					<Image>http://services.serhstourism.com/fotos/T60000/T60055_1_1.jpg</Image>
				</Images>
				<EssentialInfo>
					
				</EssentialInfo>
				<ContactInfo>
					
				</ContactInfo>
			</Hotel>
		</Hotels>
	</GetHotelsDetailsRS> 
