<?xml version="1.0" encoding="UTF-8"?>
	<GetHotelsDetailsRS Version="1">
		<Success />
		<Hotels>
			<Hotel POICode="5494558" resultcode="0" message="" >
				<Name><![CDATA[THALA BEACH LODGE]]></Name>
				<Address>
					<Address1><![CDATA[  Private Road, Oak Beach,]]></Address1>
					<Address2><![CDATA[4871, Cairns, Australia]]></Address2>
					<PostalCode>4871</PostalCode>
					<CityCode>81791</CityCode>
					<CityName lang="EN">
						<![CDATA[Cairns]]>
					</CityName>
					<CountryCode>AU</CountryCode>
					<CountryName lang="EN">
						<![CDATA[Australia]]>
					</CountryName>
				</Address>
				<GeoCode>
					<Latitude>-15.625803</Latitude>
					<Longitude>143.25725</Longitude>
				</GeoCode>
				<Rating>
					<Score><![CDATA[5]]></Score>
					<Description><![CDATA[]]></Description>
				</Rating>
				<Descriptions>
					<ShortDescriptions>
						<ShortDescription lang="EN"><![CDATA[Customers can park their car in the hotel garage. ]]></ShortDescription>
					<ShortDescription lang="EN"><![CDATA[The rooms have Laundry Service and Room-Service We also have Currency Exchange, Car parker, Shops, Safe in Reception, Garage and Business Centre.  Activities and relax: Jacuzzi, Sauna and Spa. Cuisine: . . Credit Cards: .  ]]></ShortDescription>
					</ShortDescriptions>
					<LongDescriptions>
						<LongDescription lang="EN"><![CDATA[Customers can park their car in the hotel garage. ]]></LongDescription>
					<LongDescription lang="EN"><![CDATA[The rooms have Laundry Service and Room-Service We also have Currency Exchange, Car parker, Shops, Safe in Reception, Garage and Business Centre.  Activities and relax: Jacuzzi, Sauna and Spa. Cuisine: . . Credit Cards: .  ]]></LongDescription>
					</LongDescriptions>
				</Descriptions>
				<CheckInOut>
					<CheckInTime>0</CheckInTime>
					<CheckOutTime>0</CheckOutTime>
				</CheckInOut>
				<Facilities>
					<Facility lang="EN">
						<Name><![CDATA[Other Services]]></Name>
						<Description><![CDATA[Room-Service]]></Description>	
					</Facility>
					<Facility lang="EN">
						<Name><![CDATA[Reception]]></Name>
						<Description><![CDATA[Safe in Reception]]></Description>	
					</Facility>
					<Facility lang="EN">
						<Name><![CDATA[Health and Beauty]]></Name>
						<Description><![CDATA[Spa]]></Description>	
					</Facility>
					<Facility lang="EN">
						<Name><![CDATA[Thermal Circuit]]></Name>
						<Description><![CDATA[Jacuzzi]]></Description>	
					</Facility>
					<Facility lang="EN">
						<Name><![CDATA[Other Services]]></Name>
						<Description><![CDATA[Laundry Service]]></Description>	
					</Facility>
					<Facility lang="EN">
						<Name><![CDATA[Reception]]></Name>
						<Description><![CDATA[Free Press]]></Description>	
					</Facility>
					<Facility lang="EN">
						<Name><![CDATA[Reception]]></Name>
						<Description><![CDATA[Currency Exchange]]></Description>	
					</Facility>
					<Facility lang="EN">
						<Name><![CDATA[Restaurants and Bars]]></Name>
						<Description><![CDATA[Bar Cafeteria]]></Description>	
					</Facility>
					<Facility lang="EN">
						<Name><![CDATA[Health and Beauty]]></Name>
						<Description><![CDATA[Sauna]]></Description>	
					</Facility>
					<Facility lang="EN">
						<Name><![CDATA[Reception]]></Name>
						<Description><![CDATA[Car parker]]></Description>	
					</Facility>
					<Facility lang="EN">
						<Name><![CDATA[Parking, Transfers and Hire Services]]></Name>
						<Description><![CDATA[Garage]]></Description>	
					</Facility>
				</Facilities>
				<Images>
					<Image>http://988364489.r.cdn77.net/img/poi/8319/32608319.jpg</Image>
					<Image>http://988364489.r.cdn77.net/img/poi/8320/32608320.jpg</Image>
					<Image>http://988364489.r.cdn77.net/img/poi/8321/32608321.jpg</Image>
					<Image>http://988364489.r.cdn77.net/img/poi/8316/32608316.jpg</Image>
					<Image>http://988364489.r.cdn77.net/img/poi/8317/32608317.jpg</Image>
					<Image>http://988364489.r.cdn77.net/img/poi/8318/32608318.jpg</Image>
				</Images>
				<EssentialInfo>
					
				</EssentialInfo>
				<ContactInfo>
					<Info>
						<Type>Fax</Type>
						<Content><![CDATA[+61 740985837]]></Content>
					</Info>
					<Info>
						<Type>Telephone</Type>
						<Content><![CDATA[+61 740985700 ]]></Content>
					</Info>
					
				</ContactInfo>
			</Hotel>
		</Hotels>
	</GetHotelsDetailsRS> 
