<?xml version="1.0" encoding="UTF-8"?>
	<GetHotelsDetailsRS Version="1">
		<Success />
		<Hotels>
			<Hotel POICode="5493735" resultcode="0" message="" >
				<Name><![CDATA[MAYFAIR]]></Name>
				<Address>
					<Address1><![CDATA[   Al Maktoum Road, Deira Po Box 33315,]]></Address1>
					<Address2><![CDATA[46500, Dubai, United Arab Emirates]]></Address2>
					<PostalCode>46500</PostalCode>
					<CityCode>64100</CityCode>
					<CityName lang="EN">
						<![CDATA[Dubai]]>
					</CityName>
					<CountryCode>AE</CountryCode>
					<CountryName lang="EN">
						<![CDATA[United Arab Emirates]]>
					</CountryName>
				</Address>
				<GeoCode>
					<Latitude>25.260872</Latitude>
					<Longitude>55.322937</Longitude>
				</GeoCode>
				<Rating>
					<Score><![CDATA[4]]></Score>
					<Description><![CDATA[]]></Description>
				</Rating>
				<Descriptions>
					<ShortDescriptions>
						</ShortDescriptions>
					<LongDescriptions>
						</LongDescriptions>
				</Descriptions>
				<CheckInOut>
					<CheckInTime>0</CheckInTime>
					<CheckOutTime>0</CheckOutTime>
				</CheckInOut>
				<Facilities>
				</Facilities>
				<Images>
					<Image>http://services.serhstourism.com/fotos/T21000/T21218_1_1.jpg</Image>
				</Images>
				<EssentialInfo>
					
				</EssentialInfo>
				<ContactInfo>
					
				</ContactInfo>
			</Hotel>
		</Hotels>
	</GetHotelsDetailsRS> 
