<?xml version="1.0" encoding="UTF-8"?>
	<GetHotelsDetailsRS Version="1">
		<Success />
		<Hotels>
			<Hotel POICode="6339001" resultcode="0" message="" >
				<Name><![CDATA[AL MANZIL]]></Name>
				<Address>
					<Address1><![CDATA[  P.o. Box 114822 Burj Dubai Boulevard,]]></Address1>
					<Address2><![CDATA[Dubai, Dubai, United Arab Emirates]]></Address2>
					<PostalCode>Dubai</PostalCode>
					<CityCode>64100</CityCode>
					<CityName lang="EN">
						<![CDATA[Dubai]]>
					</CityName>
					<CountryCode>AE</CountryCode>
					<CountryName lang="EN">
						<![CDATA[United Arab Emirates]]>
					</CountryName>
				</Address>
				<GeoCode>
					<Latitude>25.200724</Latitude>
					<Longitude>55.27432</Longitude>
				</GeoCode>
				<Rating>
					<Score><![CDATA[4]]></Score>
					<Description><![CDATA[]]></Description>
				</Rating>
				<Descriptions>
					<ShortDescriptions>
						</ShortDescriptions>
					<LongDescriptions>
						<LongDescription lang="EN"><![CDATA[Pets not allowed. ]]></LongDescription>
					</LongDescriptions>
				</Descriptions>
				<CheckInOut>
					<CheckInTime>0</CheckInTime>
					<CheckOutTime>0</CheckOutTime>
				</CheckInOut>
				<Facilities>
				</Facilities>
				<Images>
					<Image>http://services.serhstourism.com/fotos/E07000/E07633_1_5.jpg</Image>
					<Image>http://services.serhstourism.com/fotos/E07000/E07633_1_11.jpg</Image>
					<Image>http://services.serhstourism.com/fotos/E07000/E07633_12_14.jpg</Image>
					<Image>http://services.serhstourism.com/fotos/E07000/E07633_1_8.jpg</Image>
					<Image>http://services.serhstourism.com/fotos/E07000/E07633_1_1.jpg</Image>
					<Image>http://services.serhstourism.com/fotos/E07000/E07633_12_8.jpg</Image>
					<Image>http://services.serhstourism.com/fotos/E07000/E07633_12_3.jpg</Image>
					<Image>http://services.serhstourism.com/fotos/E07000/E07633_1_10.jpg</Image>
					<Image>http://services.serhstourism.com/fotos/E07000/E07633_1_13.jpg</Image>
					<Image>http://services.serhstourism.com/fotos/E07000/E07633_12_9.jpg</Image>
					<Image>http://services.serhstourism.com/fotos/E07000/E07633_12_13.jpg</Image>
					<Image>http://services.serhstourism.com/fotos/E07000/E07633_12_10.jpg</Image>
					<Image>http://services.serhstourism.com/fotos/E07000/E07633_1_14.jpg</Image>
					<Image>http://services.serhstourism.com/fotos/E07000/E07633_12_11.jpg</Image>
					<Image>http://services.serhstourism.com/fotos/E07000/E07633_12_1.jpg</Image>
					<Image>http://services.serhstourism.com/fotos/E07000/E07633_1_3.jpg</Image>
					<Image>http://services.serhstourism.com/fotos/E07000/E07633_1_9.jpg</Image>
					<Image>http://services.serhstourism.com/fotos/E07000/E07633_12_5.jpg</Image>
				</Images>
				<EssentialInfo>
					
				</EssentialInfo>
				<ContactInfo>
					<Info>
						<Type>Fax</Type>
						<Content><![CDATA[+971 4 428 5999]]></Content>
					</Info>
					<Info>
						<Type>Telephone</Type>
						<Content><![CDATA[+971 4 428 5888 ]]></Content>
					</Info>
					
				</ContactInfo>
			</Hotel>
		</Hotels>
	</GetHotelsDetailsRS> 
